fluentcms_googlemaps/__init__.py
fluentcms_googlemaps/admin.py
fluentcms_googlemaps/appsettings.py
fluentcms_googlemaps/content_plugins.py
fluentcms_googlemaps/models.py
fluentcms_googlemaps/urls.py
fluentcms_googlemaps/views.py
fluentcms_googlemaps/widgets.py
fluentcms_googlemaps/locale/nl/LC_MESSAGES/django.mo
fluentcms_googlemaps/locale/nl/LC_MESSAGES/django.po
fluentcms_googlemaps/management/__init__.py
fluentcms_googlemaps/management/commands/__init__.py
fluentcms_googlemaps/management/commands/import_markers.py
fluentcms_googlemaps/migrations/0001_initial.py
fluentcms_googlemaps/migrations/0002_markergroup_marker_zoom.py
fluentcms_googlemaps/migrations/__init__.py
fluentcms_googlemaps/static/fluentcms_googlemaps/admin/geopositionwidget.css
fluentcms_googlemaps/static/fluentcms_googlemaps/admin/zoomrangewidget.css
fluentcms_googlemaps/static/fluentcms_googlemaps/img/m1.png
fluentcms_googlemaps/static/fluentcms_googlemaps/img/m2.png
fluentcms_googlemaps/static/fluentcms_googlemaps/img/m3.png
fluentcms_googlemaps/static/fluentcms_googlemaps/img/m4.png
fluentcms_googlemaps/static/fluentcms_googlemaps/img/m5.png
fluentcms_googlemaps/static/fluentcms_googlemaps/js/mapplugin.js
fluentcms_googlemaps/static/fluentcms_googlemaps/js/mapsearch.js
fluentcms_googlemaps/static/fluentcms_googlemaps/vendor/markerclusterer.js
fluentcms_googlemaps/static/fluentcms_googlemaps/vendor/markerclusterer_compiled.js
fluentcms_googlemaps/static/fluentcms_googlemaps/vendor/markerwithlabel.js
fluentcms_googlemaps/templates/admin/fluentcms_googlemaps/marker/change_form.html
fluentcms_googlemaps/templates/fluentcms_googlemaps/base_map.html
fluentcms_googlemaps/templates/fluentcms_googlemaps/marker_image.html
fluentcms_googlemaps/templates/fluentcms_googlemaps/maps/default.html
fluentcms_googlemaps/templates/fluentcms_googlemaps/maps/search.html
fluentcms_googlemaps/templatetags/__init__.py
fluentcms_googlemaps/templatetags/fluentcms_googlemaps_tags.py
fluentcms_googlemaps-1.4.dist-info/DESCRIPTION.rst
fluentcms_googlemaps-1.4.dist-info/METADATA
fluentcms_googlemaps-1.4.dist-info/RECORD
fluentcms_googlemaps-1.4.dist-info/WHEEL
fluentcms_googlemaps-1.4.dist-info/metadata.json
fluentcms_googlemaps-1.4.dist-info/top_level.txt
