Metadata-Version: 2.0
Name: fluentcms-googlemaps
Version: 1.4
Summary: Google Maps widget for django-fluent-contents
Home-page: https://github.com/edoburu/fluentcms-googlemaps
Author: Diederik van der Boor
Author-email: opensource@edoburu.nl
License: Apache 2.0
Download-URL: https://github.com/edoburu/fluentcms-googlemaps/zipball/master
Platform: UNKNOWN
Classifier: Development Status :: 5 - Production/Stable
Classifier: Environment :: Web Environment
Classifier: Framework :: Django
Classifier: Intended Audience :: Developers
Classifier: License :: OSI Approved :: Apache Software License
Classifier: Operating System :: OS Independent
Classifier: Programming Language :: Python
Classifier: Programming Language :: Python :: 2.7
Classifier: Programming Language :: Python :: 3
Classifier: Programming Language :: Python :: 3.4
Classifier: Programming Language :: Python :: 3.5
Classifier: Programming Language :: Python :: 3.6
Classifier: Framework :: Django
Classifier: Framework :: Django :: 1.8
Classifier: Framework :: Django :: 1.9
Classifier: Framework :: Django :: 1.10
Classifier: Topic :: Internet :: WWW/HTTP
Classifier: Topic :: Internet :: WWW/HTTP :: Dynamic Content
Classifier: Topic :: Software Development :: Libraries :: Python Modules
Requires: Django (>=1.4)
Requires-Dist: django-fluent-contents (>=1.0)
Requires-Dist: django-geoposition (>=0.2.2)
Requires-Dist: django-wysiwyg (>=0.7.1)
Requires-Dist: geopy (>=1.10.0)
Requires-Dist: unicodecsv (>=0.13.0)
